[
  {
    "repo": "jordanbaird/Ice",
    "href": "https://github.com/jordanbaird/Ice",
    "about": "Powerful menu bar manager for macOS",
    "star": "23,063",
    "fork": "449",
    "timestamp": "2025-10-02T02:19:40.536093",
    "stars_today": "1,520 stars this month"
  },
  {
    "repo": "ml-explore/mlx-swift-examples",
    "href": "https://github.com/ml-explore/mlx-swift-examples",
    "about": "Examples using MLX Swift",
    "star": "2,230",
    "fork": "310",
    "timestamp": "2025-10-02T02:19:40.536397",
    "stars_today": "214 stars this month"
  },
  {
    "repo": "apple/container",
    "href": "https://github.com/apple/container",
    "about": "A tool for creating and running Linux containers using lightweight virtual machines on a Mac. It is written in Swift, and optimized for Apple silicon.",
    "star": "20,730",
    "fork": "454",
    "timestamp": "2025-10-02T02:19:40.536682",
    "stars_today": "1,585 stars this month"
  },
  {
    "repo": "groue/GRDB.swift",
    "href": "https://github.com/groue/GRDB.swift",
    "about": "A toolkit for SQLite databases, with a focus on application development",
    "star": "7,830",
    "fork": "788",
    "timestamp": "2025-10-02T02:19:40.536988",
    "stars_today": "100 stars this month"
  },
  {
    "repo": "CodeEditApp/CodeEdit",
    "href": "https://github.com/CodeEditApp/CodeEdit",
    "about": "📝 CodeEdit App for macOS – Elevate your code editing experience. Open source, free forever.",
    "star": "22,224",
    "fork": "1,124",
    "timestamp": "2025-10-02T02:19:40.537311",
    "stars_today": "185 stars this month"
  },
  {
    "repo": "iina/iina",
    "href": "https://github.com/iina/iina",
    "about": "The modern video player for macOS.",
    "star": "42,130",
    "fork": "2,689",
    "timestamp": "2025-10-02T02:19:40.537616",
    "stars_today": "444 stars this month"
  },
  {
    "repo": "khcrysalis/Feather",
    "href": "https://github.com/khcrysalis/Feather",
    "about": "Free on-device iOS/iPadOS application manager/installer, using certificates part of the Apple Developer Program.",
    "star": "2,878",
    "fork": "239",
    "timestamp": "2025-10-02T02:19:40.537926",
    "stars_today": "176 stars this month"
  },
  {
    "repo": "milanvarady/Applite",
    "href": "https://github.com/milanvarady/Applite",
    "about": "User-friendly GUI macOS application for Homebrew Casks",
    "star": "5,759",
    "fork": "146",
    "timestamp": "2025-10-02T02:19:40.538250",
    "stars_today": "248 stars this month"
  },
  {
    "repo": "onevcat/Kingfisher",
    "href": "https://github.com/onevcat/Kingfisher",
    "about": "A lightweight, pure-Swift library for downloading and caching images from the web.",
    "star": "24,066",
    "fork": "2,725",
    "timestamp": "2025-10-02T02:19:40.538553",
    "stars_today": "68 stars this month"
  },
  {
    "repo": "github/CopilotForXcode",
    "href": "https://github.com/github/CopilotForXcode",
    "about": "Xcode extension for GitHub Copilot",
    "star": "4,969",
    "fork": "1,335",
    "timestamp": "2025-10-02T02:19:40.538826",
    "stars_today": "227 stars this month"
  },
  {
    "repo": "mhaeuser/Battery-Toolkit",
    "href": "https://github.com/mhaeuser/Battery-Toolkit",
    "about": "Control the platform power state of your Apple Silicon Mac.",
    "star": "1,868",
    "fork": "53",
    "timestamp": "2025-10-02T02:19:40.539107",
    "stars_today": "199 stars this month"
  },
  {
    "repo": "Alamofire/Alamofire",
    "href": "https://github.com/Alamofire/Alamofire",
    "about": "Elegant HTTP Networking in Swift",
    "star": "42,138",
    "fork": "7,639",
    "timestamp": "2025-10-02T02:19:40.539401",
    "stars_today": "102 stars this month"
  },
  {
    "repo": "XcodesOrg/XcodesApp",
    "href": "https://github.com/XcodesOrg/XcodesApp",
    "about": "The easiest way to install and switch between multiple versions of Xcode - with a mouse click.",
    "star": "8,010",
    "fork": "355",
    "timestamp": "2025-10-02T02:19:40.539677",
    "stars_today": "141 stars this month"
  },
  {
    "repo": "realm/SwiftLint",
    "href": "https://github.com/realm/SwiftLint",
    "about": "A tool to enforce Swift style and conventions.",
    "star": "19,214",
    "fork": "2,268",
    "timestamp": "2025-10-02T02:19:40.539953",
    "stars_today": "75 stars this month"
  },
  {
    "repo": "LoopKit/Loop",
    "href": "https://github.com/LoopKit/Loop",
    "about": "An automated insulin delivery app for iOS, built on LoopKit",
    "star": "1,613",
    "fork": "1,355",
    "timestamp": "2025-10-02T02:19:40.540242",
    "stars_today": "17 stars this month"
  },
  {
    "repo": "overtake/TelegramSwift",
    "href": "https://github.com/overtake/TelegramSwift",
    "about": "Source code of Telegram for macos on Swift 5.0",
    "star": "5,366",
    "fork": "939",
    "timestamp": "2025-10-02T02:19:40.540514",
    "stars_today": "54 stars this month"
  },
  {
    "repo": "utmapp/UTM",
    "href": "https://github.com/utmapp/UTM",
    "about": "Virtual machines for iOS and macOS",
    "star": "31,023",
    "fork": "1,534",
    "timestamp": "2025-10-02T02:19:40.540811",
    "stars_today": "392 stars this month"
  },
  {
    "repo": "vapor/vapor",
    "href": "https://github.com/vapor/vapor",
    "about": "💧 A server-side Swift HTTP web framework.",
    "star": "25,595",
    "fork": "1,499",
    "timestamp": "2025-10-02T02:19:40.541122",
    "stars_today": "114 stars this month"
  },
  {
    "repo": "siteline/swiftui-introspect",
    "href": "https://github.com/siteline/swiftui-introspect",
    "about": "Introspect underlying UIKit/AppKit components from SwiftUI",
    "star": "6,285",
    "fork": "397",
    "timestamp": "2025-10-02T02:19:40.541394",
    "stars_today": "61 stars this month"
  },
  {
    "repo": "facebook/facebook-ios-sdk",
    "href": "https://github.com/facebook/facebook-ios-sdk",
    "about": "Used to integrate the Facebook Platform with your iOS & tvOS apps.",
    "star": "7,948",
    "fork": "3,646",
    "timestamp": "2025-10-02T02:19:40.541664",
    "stars_today": "25 stars this month"
  },
  {
    "repo": "apple/swift-async-algorithms",
    "href": "https://github.com/apple/swift-async-algorithms",
    "about": "Async Algorithms for Swift",
    "star": "3,430",
    "fork": "178",
    "timestamp": "2025-10-02T02:19:40.541933",
    "stars_today": "57 stars this month"
  }
]