[
  {
    "repo": "google-ai-edge/LiteRT-LM",
    "href": "https://github.com/google-ai-edge/LiteRT-LM",
    "about": "",
    "star": "2,630",
    "fork": "253",
    "timestamp": "2026-04-08T03:50:20.650168",
    "stars_today": "1,336 stars this week"
  },
  {
    "repo": "telegramdesktop/tdesktop",
    "href": "https://github.com/telegramdesktop/tdesktop",
    "about": "",
    "star": "31,273",
    "fork": "6,560",
    "timestamp": "2026-04-08T03:50:20.650495",
    "stars_today": "906 stars this week"
  },
  {
    "repo": "ggml-org/llama.cpp",
    "href": "https://github.com/ggml-org/llama.cpp",
    "about": "",
    "star": "102,384",
    "fork": "16,533",
    "timestamp": "2026-04-08T03:50:20.650809",
    "stars_today": "2,058 stars this week"
  },
  {
    "repo": "mozilla-ai/llamafile",
    "href": "https://github.com/mozilla-ai/llamafile",
    "about": "",
    "star": "24,050",
    "fork": "1,307",
    "timestamp": "2026-04-08T03:50:20.651138",
    "stars_today": "111 stars this week"
  },
  {
    "repo": "amnezia-vpn/amnezia-client",
    "href": "https://github.com/amnezia-vpn/amnezia-client",
    "about": "",
    "star": "11,185",
    "fork": "803",
    "timestamp": "2026-04-08T03:50:20.651447",
    "stars_today": "200 stars this week"
  },
  {
    "repo": "MrNeRF/LichtFeld-Studio",
    "href": "https://github.com/MrNeRF/LichtFeld-Studio",
    "about": "",
    "star": "2,791",
    "fork": "287",
    "timestamp": "2026-04-08T03:50:20.651782",
    "stars_today": "86 stars this week"
  },
  {
    "repo": "jellyfin/jellyfin-desktop",
    "href": "https://github.com/jellyfin/jellyfin-desktop",
    "about": "",
    "star": "289",
    "fork": "33",
    "timestamp": "2026-04-08T03:50:20.652111",
    "stars_today": "84 stars this week"
  },
  {
    "repo": "Atmosphere-NX/Atmosphere",
    "href": "https://github.com/Atmosphere-NX/Atmosphere",
    "about": "",
    "star": "18,826",
    "fork": "1,435",
    "timestamp": "2026-04-08T03:50:20.652417",
    "stars_today": "212 stars this week"
  },
  {
    "repo": "zeux/meshoptimizer",
    "href": "https://github.com/zeux/meshoptimizer",
    "about": "",
    "star": "7,539",
    "fork": "624",
    "timestamp": "2026-04-08T03:50:20.652725",
    "stars_today": "99 stars this week"
  },
  {
    "repo": "MaaAssistantArknights/MaaAssistantArknights",
    "href": "https://github.com/MaaAssistantArknights/MaaAssistantArknights",
    "about": "",
    "star": "20,229",
    "fork": "2,541",
    "timestamp": "2026-04-08T03:50:20.653046",
    "stars_today": "127 stars this week"
  },
  {
    "repo": "tdlib/td",
    "href": "https://github.com/tdlib/td",
    "about": "",
    "star": "8,650",
    "fork": "2,013",
    "timestamp": "2026-04-08T03:50:20.653351",
    "stars_today": "32 stars this week"
  },
  {
    "repo": "ml-explore/mlx-swift",
    "href": "https://github.com/ml-explore/mlx-swift",
    "about": "",
    "star": "1,733",
    "fork": "190",
    "timestamp": "2026-04-08T03:50:20.653656",
    "stars_today": "43 stars this week"
  },
  {
    "repo": "LadybirdBrowser/ladybird",
    "href": "https://github.com/LadybirdBrowser/ladybird",
    "about": "",
    "star": "62,217",
    "fork": "2,928",
    "timestamp": "2026-04-08T03:50:20.653976",
    "stars_today": "304 stars this week"
  },
  {
    "repo": "TrinityCore/TrinityCore",
    "href": "https://github.com/TrinityCore/TrinityCore",
    "about": "",
    "star": "10,499",
    "fork": "6,295",
    "timestamp": "2026-04-08T03:50:20.654281",
    "stars_today": "20 stars this week"
  },
  {
    "repo": "love2d/love",
    "href": "https://github.com/love2d/love",
    "about": "",
    "star": "8,157",
    "fork": "574",
    "timestamp": "2026-04-08T03:50:20.654584",
    "stars_today": "266 stars this week"
  },
  {
    "repo": "zhongyang219/TrafficMonitor",
    "href": "https://github.com/zhongyang219/TrafficMonitor",
    "about": "",
    "star": "43,836",
    "fork": "3,638",
    "timestamp": "2026-04-08T03:50:20.654902",
    "stars_today": "141 stars this week"
  },
  {
    "repo": "MaaXYZ/MaaFramework",
    "href": "https://github.com/MaaXYZ/MaaFramework",
    "about": "",
    "star": "3,658",
    "fork": "400",
    "timestamp": "2026-04-08T03:50:20.655211",
    "stars_today": "89 stars this week"
  },
  {
    "repo": "luanti-org/luanti",
    "href": "https://github.com/luanti-org/luanti",
    "about": "",
    "star": "12,665",
    "fork": "2,285",
    "timestamp": "2026-04-08T03:50:20.655517",
    "stars_today": "160 stars this week"
  },
  {
    "repo": "google-ai-edge/mediapipe",
    "href": "https://github.com/google-ai-edge/mediapipe",
    "about": "",
    "star": "34,589",
    "fork": "5,886",
    "timestamp": "2026-04-08T03:50:20.655822",
    "stars_today": "155 stars this week"
  },
  {
    "repo": "Adaptix-Framework/AdaptixC2",
    "href": "https://github.com/Adaptix-Framework/AdaptixC2",
    "about": "",
    "star": "2,950",
    "fork": "523",
    "timestamp": "2026-04-08T03:50:20.656142",
    "stars_today": "67 stars this week"
  },
  {
    "repo": "WerWolv/ImHex",
    "href": "https://github.com/WerWolv/ImHex",
    "about": "",
    "star": "53,092",
    "fork": "2,354",
    "timestamp": "2026-04-08T03:50:20.656475",
    "stars_today": "105 stars this week"
  }
]