[
  {
    "repo": "mostlygeek/llama-swap",
    "href": "https://github.com/mostlygeek/llama-swap",
    "about": "",
    "star": "3,458",
    "fork": "260",
    "timestamp": "2026-04-20T04:19:01.387500",
    "stars_today": "33 stars today"
  },
  {
    "repo": "XTLS/Xray-core",
    "href": "https://github.com/XTLS/Xray-core",
    "about": "",
    "star": "37,253",
    "fork": "5,198",
    "timestamp": "2026-04-20T04:19:01.387814",
    "stars_today": "52 stars today"
  },
  {
    "repo": "SagerNet/sing-box",
    "href": "https://github.com/SagerNet/sing-box",
    "about": "",
    "star": "32,854",
    "fork": "3,861",
    "timestamp": "2026-04-20T04:19:01.388100",
    "stars_today": "54 stars today"
  },
  {
    "repo": "XIU2/CloudflareSpeedTest",
    "href": "https://github.com/XIU2/CloudflareSpeedTest",
    "about": "",
    "star": "25,949",
    "fork": "4,974",
    "timestamp": "2026-04-20T04:19:01.388384",
    "stars_today": "29 stars today"
  },
  {
    "repo": "glanceapp/glance",
    "href": "https://github.com/glanceapp/glance",
    "about": "",
    "star": "33,584",
    "fork": "1,301",
    "timestamp": "2026-04-20T04:19:01.388698",
    "stars_today": "33 stars today"
  },
  {
    "repo": "aldinokemal/go-whatsapp-web-multidevice",
    "href": "https://github.com/aldinokemal/go-whatsapp-web-multidevice",
    "about": "",
    "star": "3,798",
    "fork": "897",
    "timestamp": "2026-04-20T04:19:01.389007",
    "stars_today": "6 stars today"
  },
  {
    "repo": "aquasecurity/trivy",
    "href": "https://github.com/aquasecurity/trivy",
    "about": "",
    "star": "34,613",
    "fork": "290",
    "timestamp": "2026-04-20T04:19:01.389293",
    "stars_today": "21 stars today"
  },
  {
    "repo": "tphakala/birdnet-go",
    "href": "https://github.com/tphakala/birdnet-go",
    "about": "",
    "star": "1,048",
    "fork": "91",
    "timestamp": "2026-04-20T04:19:01.389609",
    "stars_today": "11 stars today"
  },
  {
    "repo": "0xJacky/nginx-ui",
    "href": "https://github.com/0xJacky/nginx-ui",
    "about": "",
    "star": "11,066",
    "fork": "814",
    "timestamp": "2026-04-20T04:19:01.389895",
    "stars_today": "11 stars today"
  },
  {
    "repo": "cerbos/cerbos",
    "href": "https://github.com/cerbos/cerbos",
    "about": "",
    "star": "4,357",
    "fork": "176",
    "timestamp": "2026-04-20T04:19:01.390178",
    "stars_today": "8 stars today"
  },
  {
    "repo": "twpayne/chezmoi",
    "href": "https://github.com/twpayne/chezmoi",
    "about": "",
    "star": "19,249",
    "fork": "629",
    "timestamp": "2026-04-20T04:19:01.390462",
    "stars_today": "25 stars today"
  },
  {
    "repo": "avelino/awesome-go",
    "href": "https://github.com/avelino/awesome-go",
    "about": "",
    "star": "170,449",
    "fork": "13,163",
    "timestamp": "2026-04-20T04:19:01.390805",
    "stars_today": "106 stars today"
  },
  {
    "repo": "masterking32/MasterDnsVPN",
    "href": "https://github.com/masterking32/MasterDnsVPN",
    "about": "",
    "star": "760",
    "fork": "68",
    "timestamp": "2026-04-20T04:19:01.391090",
    "stars_today": "42 stars today"
  },
  {
    "repo": "v2fly/v2ray-core",
    "href": "https://github.com/v2fly/v2ray-core",
    "about": "",
    "star": "33,715",
    "fork": "5,023",
    "timestamp": "2026-04-20T04:19:01.391372",
    "stars_today": "13 stars today"
  },
  {
    "repo": "cloudflare/cloudflared",
    "href": "https://github.com/cloudflare/cloudflared",
    "about": "",
    "star": "13,895",
    "fork": "1,262",
    "timestamp": "2026-04-20T04:19:01.391664",
    "stars_today": "12 stars today"
  },
  {
    "repo": "junegunn/fzf",
    "href": "https://github.com/junegunn/fzf",
    "about": "",
    "star": "79,634",
    "fork": "2,785",
    "timestamp": "2026-04-20T04:19:01.391977",
    "stars_today": "60 stars today"
  },
  {
    "repo": "HexmosTech/git-lrc",
    "href": "https://github.com/HexmosTech/git-lrc",
    "about": "",
    "star": "712",
    "fork": "100",
    "timestamp": "2026-04-20T04:19:01.392264",
    "stars_today": "27 stars today"
  }
]