[
  {
    "repo": "lissy93/dashy",
    "href": "https://github.com/lissy93/dashy",
    "about": "",
    "star": "25,732",
    "fork": "1,881",
    "timestamp": "2026-07-07T04:51:26.280228",
    "stars_today": "175 stars this week"
  },
  {
    "repo": "RikkaApps/websites",
    "href": "https://github.com/RikkaApps/websites",
    "about": "",
    "star": "410",
    "fork": "50,574",
    "timestamp": "2026-07-07T04:51:26.280498",
    "stars_today": "7 stars this week"
  },
  {
    "repo": "CorentinTh/it-tools",
    "href": "https://github.com/CorentinTh/it-tools",
    "about": "",
    "star": "39,678",
    "fork": "5,140",
    "timestamp": "2026-07-07T04:51:26.280783",
    "stars_today": "109 stars this week"
  },
  {
    "repo": "frappe/crm",
    "href": "https://github.com/frappe/crm",
    "about": "",
    "star": "2,925",
    "fork": "1,197",
    "timestamp": "2026-07-07T04:51:26.281031",
    "stars_today": "33 stars this week"
  },
  {
    "repo": "frappe/lms",
    "href": "https://github.com/frappe/lms",
    "about": "",
    "star": "3,037",
    "fork": "1,386",
    "timestamp": "2026-07-07T04:51:26.281277",
    "stars_today": "20 stars this week"
  },
  {
    "repo": "hoowhoami/EchoMusic",
    "href": "https://github.com/hoowhoami/EchoMusic",
    "about": "",
    "star": "2,226",
    "fork": "142",
    "timestamp": "2026-07-07T04:51:26.281529",
    "stars_today": "99 stars this week"
  },
  {
    "repo": "PanJiaChen/vue-element-admin",
    "href": "https://github.com/PanJiaChen/vue-element-admin",
    "about": "",
    "star": "90,251",
    "fork": "30,419",
    "timestamp": "2026-07-07T04:51:26.281793",
    "stars_today": "21 stars this week"
  },
  {
    "repo": "miantiao-me/Sink",
    "href": "https://github.com/miantiao-me/Sink",
    "about": "",
    "star": "6,890",
    "fork": "4,842",
    "timestamp": "2026-07-07T04:51:26.282069",
    "stars_today": "32 stars this week"
  },
  {
    "repo": "yuhonas/free-exercise-db",
    "href": "https://github.com/yuhonas/free-exercise-db",
    "about": "",
    "star": "1,561",
    "fork": "426",
    "timestamp": "2026-07-07T04:51:26.282310",
    "stars_today": "44 stars this week"
  },
  {
    "repo": "primefaces/primevue",
    "href": "https://github.com/primefaces/primevue",
    "about": "",
    "star": "14,487",
    "fork": "1,736",
    "timestamp": "2026-07-07T04:51:26.282552",
    "stars_today": "7 stars this week"
  },
  {
    "repo": "zyronon/douyin",
    "href": "https://github.com/zyronon/douyin",
    "about": "",
    "star": "11,490",
    "fork": "3,094",
    "timestamp": "2026-07-07T04:51:26.282821",
    "stars_today": "14 stars this week"
  },
  {
    "repo": "beercss/beercss",
    "href": "https://github.com/beercss/beercss",
    "about": "",
    "star": "2,523",
    "fork": "94",
    "timestamp": "2026-07-07T04:51:26.283107",
    "stars_today": "82 stars this week"
  },
  {
    "repo": "aniyomiorg/aniyomi-website",
    "href": "https://github.com/aniyomiorg/aniyomi-website",
    "about": "",
    "star": "218",
    "fork": "983",
    "timestamp": "2026-07-07T04:51:26.283357",
    "stars_today": "3 stars this week"
  },
  {
    "repo": "TeamPiped/Piped",
    "href": "https://github.com/TeamPiped/Piped",
    "about": "",
    "star": "10,093",
    "fork": "869",
    "timestamp": "2026-07-07T04:51:26.283641",
    "stars_today": "32 stars this week"
  }
]