[
  {
    "repo": "cheat-engine/cheat-engine",
    "href": "https://github.com/cheat-engine/cheat-engine",
    "about": "Cheat Engine. A development environment focused on modding",
    "star": "15,926",
    "fork": "2,305",
    "timestamp": "2025-04-08T02:24:42.821302",
    "stars_today": "52 stars this week"
  },
  {
    "repo": "rejetto/hfs2",
    "href": "https://github.com/rejetto/hfs2",
    "about": "web based file server",
    "star": "638",
    "fork": "139",
    "timestamp": "2025-04-08T02:24:42.821640",
    "stars_today": "1 star this week"
  },
  {
    "repo": "jrsoftware/issrc",
    "href": "https://github.com/jrsoftware/issrc",
    "about": "Inno Setup is a free installer for Windows programs. First introduced in 1997, Inno Setup today rivals and even surpasses many commercial installers in feature set and stability.",
    "star": "4,566",
    "fork": "966",
    "timestamp": "2025-04-08T02:24:42.821931",
    "stars_today": "8 stars this week"
  },
  {
    "repo": "doublecmd/doublecmd",
    "href": "https://github.com/doublecmd/doublecmd",
    "about": "Double Commander is a free cross platform open source file manager with two panels side by side.",
    "star": "3,099",
    "fork": "220",
    "timestamp": "2025-04-08T02:24:42.822219",
    "stars_today": "18 stars this week"
  },
  {
    "repo": "peazip/PeaZip",
    "href": "https://github.com/peazip/PeaZip",
    "about": "Free Zip / Unzip software and Rar file extractor. Cross-platform file and archive manager. Features volume spanning, compression, authenticated encryption. Supports 7Z, 7-Zip sfx, ACE, ARJ, Brotli, BZ2, CAB, CHM, CPIO, DEB, GZ, ISO, JAR, LHA/LZH, NSIS, OOo, PAQ/LPAQ, PEA, QUAD, RAR, RPM, split, TAR, Z, ZIP, ZIPX, Zstandard.",
    "star": "4,955",
    "fork": "272",
    "timestamp": "2025-04-08T02:24:42.822501",
    "stars_today": "25 stars this week"
  },
  {
    "repo": "tarcode-apps/BatteryMode",
    "href": "https://github.com/tarcode-apps/BatteryMode",
    "about": "Windows Battery Indicator replacement",
    "star": "322",
    "fork": "17",
    "timestamp": "2025-04-08T02:24:42.822796",
    "stars_today": "2 stars this week"
  },
  {
    "repo": "UltraStar-Deluxe/USDX",
    "href": "https://github.com/UltraStar-Deluxe/USDX",
    "about": "The free and open source karaoke singing game UltraStar Deluxe, inspired by Sony SingStar™",
    "star": "938",
    "fork": "169",
    "timestamp": "2025-04-08T02:24:42.823078",
    "stars_today": "3 stars this week"
  },
  {
    "repo": "nofeletru/UsbAsp-flash",
    "href": "https://github.com/nofeletru/UsbAsp-flash",
    "about": "Program allow you to program flash memory on the protocols spi, I2C, MicroWire. Supports CH341a, CH347, UsbAsp, AVRISP(LUFA), Arduino, FT232H.",
    "star": "1,032",
    "fork": "206",
    "timestamp": "2025-04-08T02:24:42.823361",
    "stars_today": "4 stars this week"
  }
]