[
  {
    "repo": "LMS-Community/slimserver",
    "href": "https://github.com/LMS-Community/slimserver",
    "about": "Server for Squeezebox and compatible players. This server is also called Lyrion Music Server.",
    "star": "1,591",
    "fork": "343",
    "timestamp": "2025-12-26T02:52:35.231540",
    "stars_today": "18 stars this week"
  },
  {
    "repo": "exiftool/exiftool",
    "href": "https://github.com/exiftool/exiftool",
    "about": "ExifTool meta information reader/writer",
    "star": "4,277",
    "fork": "400",
    "timestamp": "2025-12-26T02:52:35.231873",
    "stars_today": "23 stars this week"
  },
  {
    "repo": "michaelherger/Spotty-Plugin",
    "href": "https://github.com/michaelherger/Spotty-Plugin",
    "about": "A Spotify plugin for the Lyrion Music Server (fka. Logitech Media Server) and Squeezebox compatible players",
    "star": "176",
    "fork": "30",
    "timestamp": "2025-12-26T02:52:35.232156",
    "stars_today": "9 stars this week"
  },
  {
    "repo": "holzschu/a-shell",
    "href": "https://github.com/holzschu/a-shell",
    "about": "A terminal for iOS, with multiple windows",
    "star": "3,412",
    "fork": "161",
    "timestamp": "2025-12-26T02:52:35.232446",
    "stars_today": "19 stars this week"
  },
  {
    "repo": "brendangregg/FlameGraph",
    "href": "https://github.com/brendangregg/FlameGraph",
    "about": "Stack trace visualizer",
    "star": "19,088",
    "fork": "2,073",
    "timestamp": "2025-12-26T02:52:35.232733",
    "stars_today": "19 stars this week"
  },
  {
    "repo": "znuny/Znuny",
    "href": "https://github.com/znuny/Znuny",
    "about": "Znuny is a free, open-source, and versatile web-based ticketing system for Customer Service, Help Desk, IT Service Management, and more. It is built for transparency and long-term sustainability and is highly tailorable to your organization's needs.",
    "star": "531",
    "fork": "113",
    "timestamp": "2025-12-26T02:52:35.233035",
    "stars_today": "2 stars this week"
  },
  {
    "repo": "inverse-inc/packetfence",
    "href": "https://github.com/inverse-inc/packetfence",
    "about": "PacketFence is a fully supported, trusted, Free and Open Source network access control (NAC) solution. Boasting an impressive feature set including a captive-portal for registration and remediation, centralized wired and wireless management, powerful BYOD management options, 802.1X support, layer-2 isolation of problematic devices; PacketFence c…",
    "star": "1,569",
    "fork": "311",
    "timestamp": "2025-12-26T02:52:35.233324",
    "stars_today": "2 stars this week"
  },
  {
    "repo": "ddclient/ddclient",
    "href": "https://github.com/ddclient/ddclient",
    "about": "ddclient updates dynamic DNS entries for accounts on a wide range of dynamic DNS services.",
    "star": "3,259",
    "fork": "379",
    "timestamp": "2025-12-26T02:52:35.233609",
    "stars_today": "14 stars this week"
  },
  {
    "repo": "linux-test-project/lcov",
    "href": "https://github.com/linux-test-project/lcov",
    "about": "LCOV",
    "star": "1,055",
    "fork": "259",
    "timestamp": "2025-12-26T02:52:35.233909",
    "stars_today": "5 stars this week"
  },
  {
    "repo": "Aetherinox/csf-firewall",
    "href": "https://github.com/Aetherinox/csf-firewall",
    "about": "ConfigServer Security & Firewall (CSF) - Robust linux iptables/nftables firewall & free ipset blocklist service.",
    "star": "225",
    "fork": "41",
    "timestamp": "2025-12-26T02:52:35.234228",
    "stars_today": "8 stars this week"
  },
  {
    "repo": "adrienverge/openfortivpn",
    "href": "https://github.com/adrienverge/openfortivpn",
    "about": "Client for PPP+TLS VPN tunnel services",
    "star": "3,159",
    "fork": "360",
    "timestamp": "2025-12-26T02:52:35.234547",
    "stars_today": "9 stars this week"
  }
]