[
  {
    "repo": "systemd/systemd",
    "href": "https://github.com/systemd/systemd",
    "about": "",
    "star": "16,113",
    "fork": "4,410",
    "timestamp": "2026-03-28T03:35:11.106962",
    "stars_today": "714 stars this week"
  },
  {
    "repo": "opa334/Dopamine",
    "href": "https://github.com/opa334/Dopamine",
    "about": "",
    "star": "4,805",
    "fork": "6,025",
    "timestamp": "2026-03-28T03:35:11.107303",
    "stars_today": "94 stars this week"
  },
  {
    "repo": "containers/bubblewrap",
    "href": "https://github.com/containers/bubblewrap",
    "about": "",
    "star": "6,324",
    "fork": "299",
    "timestamp": "2026-03-28T03:35:11.107642",
    "stars_today": "137 stars this week"
  },
  {
    "repo": "kingToolbox/WindTerm",
    "href": "https://github.com/kingToolbox/WindTerm",
    "about": "",
    "star": "30,267",
    "fork": "2,310",
    "timestamp": "2026-03-28T03:35:11.107955",
    "stars_today": "160 stars this week"
  },
  {
    "repo": "dune3d/dune3d",
    "href": "https://github.com/dune3d/dune3d",
    "about": "",
    "star": "1,878",
    "fork": "79",
    "timestamp": "2026-03-28T03:35:11.108260",
    "stars_today": "295 stars this week"
  },
  {
    "repo": "paxx12/SnapmakerU1-Extended-Firmware",
    "href": "https://github.com/paxx12/SnapmakerU1-Extended-Firmware",
    "about": "",
    "star": "479",
    "fork": "60",
    "timestamp": "2026-03-28T03:35:11.108632",
    "stars_today": "45 stars this week"
  },
  {
    "repo": "TelegramMessenger/MTProxy",
    "href": "https://github.com/TelegramMessenger/MTProxy",
    "about": "",
    "star": "6,454",
    "fork": "1,066",
    "timestamp": "2026-03-28T03:35:11.108940",
    "stars_today": "149 stars this week"
  },
  {
    "repo": "CTCaer/hekate",
    "href": "https://github.com/CTCaer/hekate",
    "about": "",
    "star": "8,214",
    "fork": "645",
    "timestamp": "2026-03-28T03:35:11.109342",
    "stars_today": "53 stars this week"
  },
  {
    "repo": "ventoy/Ventoy",
    "href": "https://github.com/ventoy/Ventoy",
    "about": "",
    "star": "75,322",
    "fork": "4,722",
    "timestamp": "2026-03-28T03:35:11.109904",
    "stars_today": "185 stars this week"
  },
  {
    "repo": "andreknieriem/headunit-revived",
    "href": "https://github.com/andreknieriem/headunit-revived",
    "about": "",
    "star": "531",
    "fork": "42",
    "timestamp": "2026-03-28T03:35:11.110360",
    "stars_today": "52 stars this week"
  },
  {
    "repo": "bol-van/zapret",
    "href": "https://github.com/bol-van/zapret",
    "about": "",
    "star": "14,779",
    "fork": "1,021",
    "timestamp": "2026-03-28T03:35:11.110707",
    "stars_today": "116 stars this week"
  },
  {
    "repo": "zephyrproject-rtos/zephyr",
    "href": "https://github.com/zephyrproject-rtos/zephyr",
    "about": "",
    "star": "14,821",
    "fork": "8,880",
    "timestamp": "2026-03-28T03:35:11.111026",
    "stars_today": "74 stars this week"
  },
  {
    "repo": "bytecodealliance/wasm-micro-runtime",
    "href": "https://github.com/bytecodealliance/wasm-micro-runtime",
    "about": "",
    "star": "5,859",
    "fork": "774",
    "timestamp": "2026-03-28T03:35:11.111340",
    "stars_today": "29 stars this week"
  },
  {
    "repo": "OpenMathLib/OpenBLAS",
    "href": "https://github.com/OpenMathLib/OpenBLAS",
    "about": "",
    "star": "7,357",
    "fork": "1,657",
    "timestamp": "2026-03-28T03:35:11.111670",
    "stars_today": "19 stars this week"
  },
  {
    "repo": "coturn/coturn",
    "href": "https://github.com/coturn/coturn",
    "about": "",
    "star": "13,796",
    "fork": "2,219",
    "timestamp": "2026-03-28T03:35:11.111984",
    "stars_today": "51 stars this week"
  },
  {
    "repo": "apache/nuttx",
    "href": "https://github.com/apache/nuttx",
    "about": "",
    "star": "3,760",
    "fork": "1,526",
    "timestamp": "2026-03-28T03:35:11.112297",
    "stars_today": "18 stars this week"
  },
  {
    "repo": "PufferAI/PufferLib",
    "href": "https://github.com/PufferAI/PufferLib",
    "about": "",
    "star": "5,320",
    "fork": "416",
    "timestamp": "2026-03-28T03:35:11.112631",
    "stars_today": "124 stars this week"
  },
  {
    "repo": "nginx/nginx",
    "href": "https://github.com/nginx/nginx",
    "about": "",
    "star": "29,768",
    "fork": "7,825",
    "timestamp": "2026-03-28T03:35:11.112947",
    "stars_today": "112 stars this week"
  }
]