[
  {
    "repo": "ziglang/zig",
    "href": "https://github.com/ziglang/zig",
    "about": "General-purpose programming language and toolchain for maintaining robust, optimal, and reusable software.",
    "star": "35,289",
    "fork": "2,576",
    "timestamp": "2024-12-07T02:24:30.009848",
    "stars_today": "16 stars today"
  },
  {
    "repo": "NilsIrl/dockerc",
    "href": "https://github.com/NilsIrl/dockerc",
    "about": "container image to single executable compiler",
    "star": "3,767",
    "fork": "75",
    "timestamp": "2024-12-07T02:24:30.010158",
    "stars_today": "173 stars today"
  },
  {
    "repo": "tigerbeetle/tigerbeetle",
    "href": "https://github.com/tigerbeetle/tigerbeetle",
    "about": "The financial transactions database designed for mission critical safety and performance.",
    "star": "10,779",
    "fork": "519",
    "timestamp": "2024-12-07T02:24:30.010450",
    "stars_today": "36 stars today"
  },
  {
    "repo": "oven-sh/bun",
    "href": "https://github.com/oven-sh/bun",
    "about": "Incredibly fast JavaScript runtime, bundler, test runner, and package manager – all in one",
    "star": "74,569",
    "fork": "2,784",
    "timestamp": "2024-12-07T02:24:30.010745",
    "stars_today": "22 stars today"
  },
  {
    "repo": "kristoff-it/zine",
    "href": "https://github.com/kristoff-it/zine",
    "about": "Fast, Scalable, Flexible Static Site Generator (SSG)",
    "star": "670",
    "fork": "40",
    "timestamp": "2024-12-07T02:24:30.011074",
    "stars_today": "1 star today"
  },
  {
    "repo": "mitchellh/libxev",
    "href": "https://github.com/mitchellh/libxev",
    "about": "libxev is a cross-platform, high-performance event loop that provides abstractions for non-blocking IO, timers, events, and more and works on Linux (io_uring or epoll), macOS (kqueue), and Wasm + WASI. Available as both a Zig and C API.",
    "star": "2,174",
    "fork": "78",
    "timestamp": "2024-12-07T02:24:30.011373",
    "stars_today": "1 star today"
  },
  {
    "repo": "tiehuis/zig-regex",
    "href": "https://github.com/tiehuis/zig-regex",
    "about": "A regex implementation for the zig programming language",
    "star": "203",
    "fork": "24",
    "timestamp": "2024-12-07T02:24:30.011672",
    "stars_today": "1 star today"
  },
  {
    "repo": "pedropark99/zig-book",
    "href": "https://github.com/pedropark99/zig-book",
    "about": "An open, technical and introductory book for the Zig programming language",
    "star": "642",
    "fork": "27",
    "timestamp": "2024-12-07T02:24:30.011981",
    "stars_today": "1 star today"
  },
  {
    "repo": "ZigEmbeddedGroup/microzig",
    "href": "https://github.com/ZigEmbeddedGroup/microzig",
    "about": "Unified abstraction layer and HAL for several microcontrollers",
    "star": "1,272",
    "fork": "103",
    "timestamp": "2024-12-07T02:24:30.012276",
    "stars_today": "1 star today"
  }
]