[
  {
    "repo": "khanhduytran0/LiveContainer",
    "href": "https://github.com/khanhduytran0/LiveContainer",
    "about": "Run iOS app without actually installing it!",
    "star": "1,853",
    "fork": "268",
    "timestamp": "2025-04-07T02:28:35.339388",
    "stars_today": "37 stars this week"
  },
  {
    "repo": "ReactiveX/RxSwift",
    "href": "https://github.com/ReactiveX/RxSwift",
    "about": "Reactive Programming in Swift",
    "star": "24,534",
    "fork": "4,182",
    "timestamp": "2025-04-07T02:28:35.339687",
    "stars_today": "16 stars this week"
  },
  {
    "repo": "Dimillian/IceCubesApp",
    "href": "https://github.com/Dimillian/IceCubesApp",
    "about": "A SwiftUI Mastodon client",
    "star": "6,067",
    "fork": "590",
    "timestamp": "2025-04-07T02:28:35.339994",
    "stars_today": "108 stars this week"
  },
  {
    "repo": "pointfreeco/swift-dependencies",
    "href": "https://github.com/pointfreeco/swift-dependencies",
    "about": "A dependency management library inspired by SwiftUI's \"environment.\"",
    "star": "1,777",
    "fork": "145",
    "timestamp": "2025-04-07T02:28:35.340303",
    "stars_today": "20 stars this week"
  },
  {
    "repo": "RevenueCat/purchases-ios",
    "href": "https://github.com/RevenueCat/purchases-ios",
    "about": "In-app purchases and subscriptions made easy. Support for iOS, watchOS, tvOS, macOS, and visionOS.",
    "star": "2,545",
    "fork": "348",
    "timestamp": "2025-04-07T02:28:35.340579",
    "stars_today": "23 stars this week"
  },
  {
    "repo": "pointfreeco/swift-composable-architecture",
    "href": "https://github.com/pointfreeco/swift-composable-architecture",
    "about": "A library for building applications in a consistent and understandable way, with composition, testing, and ergonomics in mind.",
    "star": "13,087",
    "fork": "1,509",
    "timestamp": "2025-04-07T02:28:35.340850",
    "stars_today": "23 stars this week"
  },
  {
    "repo": "exelban/stats",
    "href": "https://github.com/exelban/stats",
    "about": "macOS system monitor in your menu bar",
    "star": "30,409",
    "fork": "961",
    "timestamp": "2025-04-07T02:28:35.341164",
    "stars_today": "167 stars this week"
  },
  {
    "repo": "realm/SwiftLint",
    "href": "https://github.com/realm/SwiftLint",
    "about": "A tool to enforce Swift style and conventions.",
    "star": "18,910",
    "fork": "2,243",
    "timestamp": "2025-04-07T02:28:35.341442",
    "stars_today": "20 stars this week"
  },
  {
    "repo": "Whisky-App/Whisky",
    "href": "https://github.com/Whisky-App/Whisky",
    "about": "A modern Wine wrapper for macOS built with SwiftUI",
    "star": "14,277",
    "fork": "321",
    "timestamp": "2025-04-07T02:28:35.341712",
    "stars_today": "63 stars this week"
  },
  {
    "repo": "XcodesOrg/XcodesApp",
    "href": "https://github.com/XcodesOrg/XcodesApp",
    "about": "The easiest way to install and switch between multiple versions of Xcode - with a mouse click.",
    "star": "7,398",
    "fork": "322",
    "timestamp": "2025-04-07T02:28:35.341986",
    "stars_today": "64 stars this week"
  },
  {
    "repo": "rileytestut/Delta",
    "href": "https://github.com/rileytestut/Delta",
    "about": "Delta is an all-in-one classic video game emulator for non-jailbroken iOS devices.",
    "star": "5,152",
    "fork": "382",
    "timestamp": "2025-04-07T02:28:35.342272",
    "stars_today": "60 stars this week"
  },
  {
    "repo": "khcrysalis/Feather",
    "href": "https://github.com/khcrysalis/Feather",
    "about": "Feather is a free on-device iOS application manager/installer, using certificates part of the Apple Developer Program.",
    "star": "1,813",
    "fork": "129",
    "timestamp": "2025-04-07T02:28:35.342571",
    "stars_today": "62 stars this week"
  },
  {
    "repo": "XcodesOrg/xcodes",
    "href": "https://github.com/XcodesOrg/xcodes",
    "about": "The best command-line tool to install and switch between multiple versions of Xcode.",
    "star": "4,035",
    "fork": "145",
    "timestamp": "2025-04-07T02:28:35.342844",
    "stars_today": "34 stars this week"
  },
  {
    "repo": "lihaoyun6/QuickRecorder",
    "href": "https://github.com/lihaoyun6/QuickRecorder",
    "about": "A lightweight screen recorder based on ScreenCapture Kit for macOS / 基于 ScreenCapture Kit 的轻量化多功能 macOS 录屏工具",
    "star": "5,741",
    "fork": "296",
    "timestamp": "2025-04-07T02:28:35.343131",
    "stars_today": "68 stars this week"
  },
  {
    "repo": "nicklockwood/SwiftFormat",
    "href": "https://github.com/nicklockwood/SwiftFormat",
    "about": "A command-line tool and Xcode Extension for formatting Swift code",
    "star": "8,195",
    "fork": "638",
    "timestamp": "2025-04-07T02:28:35.343402",
    "stars_today": "10 stars this week"
  },
  {
    "repo": "seemoo-lab/openhaystack",
    "href": "https://github.com/seemoo-lab/openhaystack",
    "about": "Build your own 'AirTags' 🏷 today! Framework for tracking personal Bluetooth devices via Apple's massive Find My network.",
    "star": "11,241",
    "fork": "533",
    "timestamp": "2025-04-07T02:28:35.343676",
    "stars_today": "91 stars this week"
  },
  {
    "repo": "pointfreeco/swift-snapshot-testing",
    "href": "https://github.com/pointfreeco/swift-snapshot-testing",
    "about": "📸 Delightful Swift snapshot testing.",
    "star": "3,903",
    "fork": "603",
    "timestamp": "2025-04-07T02:28:35.343947",
    "stars_today": "8 stars this week"
  },
  {
    "repo": "krzyzanowskim/CryptoSwift",
    "href": "https://github.com/krzyzanowskim/CryptoSwift",
    "about": "CryptoSwift is a growing collection of standard and secure cryptographic algorithms implemented in Swift",
    "star": "10,312",
    "fork": "1,707",
    "timestamp": "2025-04-07T02:28:35.344258",
    "stars_today": "7 stars this week"
  },
  {
    "repo": "Caldis/Mos",
    "href": "https://github.com/Caldis/Mos",
    "about": "一个用于在 macOS 上平滑你的鼠标滚动效果或单独设置滚动方向的小工具, 让你的滚轮爽如触控板 | A lightweight tool used to smooth scrolling and set scroll direction independently for your mouse on macOS",
    "star": "16,318",
    "fork": "547",
    "timestamp": "2025-04-07T02:28:35.344530",
    "stars_today": "100 stars this week"
  },
  {
    "repo": "signalapp/Signal-iOS",
    "href": "https://github.com/signalapp/Signal-iOS",
    "about": "A private messenger for iOS.",
    "star": "11,172",
    "fork": "3,161",
    "timestamp": "2025-04-07T02:28:35.344799",
    "stars_today": "25 stars this week"
  },
  {
    "repo": "getsentry/sentry-cocoa",
    "href": "https://github.com/getsentry/sentry-cocoa",
    "about": "The official Sentry SDK for iOS, tvOS, macOS, watchOS.",
    "star": "866",
    "fork": "341",
    "timestamp": "2025-04-07T02:28:35.345079",
    "stars_today": "3 stars this week"
  },
  {
    "repo": "siteline/swiftui-introspect",
    "href": "https://github.com/siteline/swiftui-introspect",
    "about": "Introspect underlying UIKit/AppKit components from SwiftUI",
    "star": "5,970",
    "fork": "363",
    "timestamp": "2025-04-07T02:28:35.345349",
    "stars_today": "18 stars this week"
  },
  {
    "repo": "p0deje/Maccy",
    "href": "https://github.com/p0deje/Maccy",
    "about": "Lightweight clipboard manager for macOS",
    "star": "14,653",
    "fork": "619",
    "timestamp": "2025-04-07T02:28:35.345618",
    "stars_today": "92 stars this week"
  }
]